{
    "_links": {
        "self": {
            "href": "http:\/\/default\/article\/molior-natu-quidne-valde?_format=hal_json"
        },
        "type": {
            "href": "http:\/\/drupal.org\/rest\/type\/node\/article"
        },
        "http:\/\/drupal.org\/rest\/relation\/node\/article\/revision_uid": [
            {
                "href": "http:\/\/default\/user\/1?_format=hal_json"
            }
        ],
        "http:\/\/drupal.org\/rest\/relation\/node\/article\/uid": [
            {
                "href": "http:\/\/default\/user\/0?_format=hal_json",
                "lang": "en"
            }
        ],
        "http:\/\/drupal.org\/rest\/relation\/node\/article\/field_image": [
            {
                "href": "http:\/\/default\/sites\/default\/files\/2020-05\/f8bc126d97c41b8b165d0d.jpg",
                "lang": "en"
            }
        ],
        "http:\/\/drupal.org\/rest\/relation\/node\/article\/field_paragraph_selector": [
            {
                "href": ""
            },
            {
                "href": ""
            },
            {
                "href": ""
            },
            {
                "href": ""
            },
            {
                "href": ""
            },
            {
                "href": ""
            },
            {
                "href": ""
            },
            {
                "href": ""
            },
            {
                "href": ""
            },
            {
                "href": ""
            }
        ],
        "http:\/\/drupal.org\/rest\/relation\/node\/article\/field_tags": [
            {
                "href": "http:\/\/default\/food?_format=hal_json",
                "lang": "en"
            },
            {
                "href": "http:\/\/default\/comedy?_format=hal_json",
                "lang": "en"
            },
            {
                "href": "http:\/\/default\/leisure?_format=hal_json",
                "lang": "en"
            }
        ]
    },
    "uuid": [
        {
            "value": "88fe42e0-561c-49a6-9ed2-396c4cf1a3fb"
        }
    ],
    "langcode": [
        {
            "value": "en",
            "lang": "en"
        }
    ],
    "type": [
        {
            "target_id": "article"
        }
    ],
    "revision_timestamp": [
        {
            "value": "2020-05-17T22:22:50+00:00",
            "format": "Y-m-d\\TH:i:sP"
        }
    ],
    "_embedded": {
        "http:\/\/drupal.org\/rest\/relation\/node\/article\/revision_uid": [
            {
                "_links": {
                    "self": {
                        "href": "http:\/\/default\/user\/1?_format=hal_json"
                    },
                    "type": {
                        "href": "http:\/\/drupal.org\/rest\/type\/user\/user"
                    }
                },
                "uuid": [
                    {
                        "value": "63e76125-7371-4f7a-b81d-035ad7ffe915"
                    }
                ]
            }
        ],
        "http:\/\/drupal.org\/rest\/relation\/node\/article\/uid": [
            {
                "_links": {
                    "self": {
                        "href": "http:\/\/default\/user\/0?_format=hal_json"
                    },
                    "type": {
                        "href": "http:\/\/drupal.org\/rest\/type\/user\/user"
                    }
                },
                "uuid": [
                    {
                        "value": "7251a64d-2d53-4619-b8ac-fe8ae42fee34"
                    }
                ],
                "lang": "en"
            }
        ],
        "http:\/\/drupal.org\/rest\/relation\/node\/article\/field_image": [
            {
                "_links": {
                    "self": {
                        "href": "http:\/\/default\/sites\/default\/files\/2020-05\/f8bc126d97c41b8b165d0d.jpg"
                    },
                    "type": {
                        "href": "http:\/\/drupal.org\/rest\/type\/file\/file"
                    }
                },
                "uuid": [
                    {
                        "value": "ecbfa1b7-2886-4f5a-8216-686b95bab2ab"
                    }
                ],
                "lang": "en"
            }
        ],
        "http:\/\/drupal.org\/rest\/relation\/node\/article\/field_paragraph_selector": [
            {
                "_links": {
                    "self": {
                        "href": ""
                    },
                    "type": {
                        "href": "http:\/\/drupal.org\/rest\/type\/paragraph\/news_paragraph"
                    }
                },
                "uuid": [
                    {
                        "value": "277a990d-8cd8-4236-9a2e-07f79b9efb66"
                    }
                ],
                "target_revision_id": "240"
            },
            {
                "_links": {
                    "self": {
                        "href": ""
                    },
                    "type": {
                        "href": "http:\/\/drupal.org\/rest\/type\/paragraph\/news_paragraph"
                    }
                },
                "uuid": [
                    {
                        "value": "9ee9d303-e433-4a67-b472-cb32ac2188f5"
                    }
                ],
                "target_revision_id": "241"
            },
            {
                "_links": {
                    "self": {
                        "href": ""
                    },
                    "type": {
                        "href": "http:\/\/drupal.org\/rest\/type\/paragraph\/news_paragraph"
                    }
                },
                "uuid": [
                    {
                        "value": "226bfaff-2cf3-47bd-9467-b5235bcde7df"
                    }
                ],
                "target_revision_id": "242"
            },
            {
                "_links": {
                    "self": {
                        "href": ""
                    },
                    "type": {
                        "href": "http:\/\/drupal.org\/rest\/type\/paragraph\/news_paragraph"
                    }
                },
                "uuid": [
                    {
                        "value": "cf92c42c-240f-451a-9860-1d15de29b908"
                    }
                ],
                "target_revision_id": "243"
            },
            {
                "_links": {
                    "self": {
                        "href": ""
                    },
                    "type": {
                        "href": "http:\/\/drupal.org\/rest\/type\/paragraph\/news_paragraph"
                    }
                },
                "uuid": [
                    {
                        "value": "65ec5996-c231-4376-820f-f4207cab74ac"
                    }
                ],
                "target_revision_id": "244"
            },
            {
                "_links": {
                    "self": {
                        "href": ""
                    },
                    "type": {
                        "href": "http:\/\/drupal.org\/rest\/type\/paragraph\/news_paragraph"
                    }
                },
                "uuid": [
                    {
                        "value": "05f06b7d-19a5-485f-8828-20244539c870"
                    }
                ],
                "target_revision_id": "245"
            },
            {
                "_links": {
                    "self": {
                        "href": ""
                    },
                    "type": {
                        "href": "http:\/\/drupal.org\/rest\/type\/paragraph\/news_paragraph"
                    }
                },
                "uuid": [
                    {
                        "value": "dd0973f3-e2aa-4771-9ae1-b83c7ed16027"
                    }
                ],
                "target_revision_id": "246"
            },
            {
                "_links": {
                    "self": {
                        "href": ""
                    },
                    "type": {
                        "href": "http:\/\/drupal.org\/rest\/type\/paragraph\/news_paragraph"
                    }
                },
                "uuid": [
                    {
                        "value": "55de269f-76c9-4c41-ab56-58c4b562842c"
                    }
                ],
                "target_revision_id": "247"
            },
            {
                "_links": {
                    "self": {
                        "href": ""
                    },
                    "type": {
                        "href": "http:\/\/drupal.org\/rest\/type\/paragraph\/news_paragraph"
                    }
                },
                "uuid": [
                    {
                        "value": "7776f821-624a-4d12-8ce3-1a0e9f9c1323"
                    }
                ],
                "target_revision_id": "248"
            },
            {
                "_links": {
                    "self": {
                        "href": ""
                    },
                    "type": {
                        "href": "http:\/\/drupal.org\/rest\/type\/paragraph\/news_paragraph"
                    }
                },
                "uuid": [
                    {
                        "value": "d0c17f71-b3df-492a-a9e0-c1ff16472452"
                    }
                ],
                "target_revision_id": "249"
            }
        ],
        "http:\/\/drupal.org\/rest\/relation\/node\/article\/field_tags": [
            {
                "_links": {
                    "self": {
                        "href": "http:\/\/default\/food?_format=hal_json"
                    },
                    "type": {
                        "href": "http:\/\/drupal.org\/rest\/type\/taxonomy_term\/category"
                    }
                },
                "uuid": [
                    {
                        "value": "d6c18919-f12b-4a2a-a347-26208bc48772"
                    }
                ],
                "lang": "en"
            },
            {
                "_links": {
                    "self": {
                        "href": "http:\/\/default\/comedy?_format=hal_json"
                    },
                    "type": {
                        "href": "http:\/\/drupal.org\/rest\/type\/taxonomy_term\/category"
                    }
                },
                "uuid": [
                    {
                        "value": "d381bea5-c422-40b0-aea8-667b5343d56f"
                    }
                ],
                "lang": "en"
            },
            {
                "_links": {
                    "self": {
                        "href": "http:\/\/default\/leisure?_format=hal_json"
                    },
                    "type": {
                        "href": "http:\/\/drupal.org\/rest\/type\/taxonomy_term\/category"
                    }
                },
                "uuid": [
                    {
                        "value": "50080f52-7164-4ecc-a673-bcab342426ab"
                    }
                ],
                "lang": "en"
            }
        ]
    },
    "status": [
        {
            "value": true,
            "lang": "en"
        }
    ],
    "title": [
        {
            "value": "Molior Natu Quidne Valde",
            "lang": "en"
        }
    ],
    "created": [
        {
            "value": "2019-07-29T10:50:48+00:00",
            "lang": "en",
            "format": "Y-m-d\\TH:i:sP"
        }
    ],
    "changed": [
        {
            "value": "2020-05-17T22:22:50+00:00",
            "lang": "en",
            "format": "Y-m-d\\TH:i:sP"
        }
    ],
    "promote": [
        {
            "value": true,
            "lang": "en"
        }
    ],
    "sticky": [
        {
            "value": false,
            "lang": "en"
        }
    ],
    "default_langcode": [
        {
            "value": true,
            "lang": "en"
        }
    ],
    "revision_translation_affected": [
        {
            "value": true,
            "lang": "en"
        }
    ],
    "path": [
        {
            "alias": "\/article\/molior-natu-quidne-valde",
            "pid": 16,
            "langcode": "en",
            "lang": "en"
        }
    ],
    "body": [
        {
            "value": "Abico amet antehabeo capto imputo olim quae sudo suscipit typicus. Ille lobortis neque olim os praemitto ratis refero ut. Decet et eum metuo nostrud pala paratus valetudo vicis. Fere nutus vereor. Adipiscing at jugis loquor minim odio. Aliquam blandit caecus immitto natu neque os suscipere verto.\r\n\r\nBrevitas jumentum sit tum. Euismod quia quis volutpat. Gilvus saluto sudo. Autem caecus eum luptatum oppeto os sed verto. Eros minim odio. Accumsan antehabeo enim hendrerit quibus. Aliquip os singularis.\r\n\r\nEum facilisi olim quadrum. Imputo mauris obruo odio si validus. Amet conventio distineo genitus humo ille refero secundum singularis validus. Eligo immitto ludus quae. Elit exerci iaceo ideo patria secundum vel.\r\n\r\nDamnum ex ille imputo turpis valetudo. Cui dignissim dolor nobis praesent quidne. Amet fere imputo validus. Et interdico nibh nutus quibus torqueo. Camur dignissim dolore eum genitus modo refero ulciscor vulputate.\r\n\r\nCommoveo iustum modo refero tum turpis. Aliquip amet bene capto diam genitus interdico quibus valde. Eligo haero luctus pertineo plaga tum valde. Abbas adipiscing sino tamen. Aptent causa ibidem jugis nutus sudo torqueo valetudo vulpes.\r\n\r\nAcsi aptent comis proprius. Eros facilisis gilvus plaga quibus vel vicis. Ad blandit commoveo elit pertineo. Acsi antehabeo bene oppeto plaga ullamcorper venio. Causa comis conventio distineo esca facilisi gilvus melior obruo suscipere.\r\n\r\nCaecus fere iustum olim refero roto sit vicis. Gravis humo iustum lucidus pertineo tation typicus. Diam eligo importunus lucidus. At bene dignissim. Abigo camur fere imputo nimis nulla olim pertineo praemitto. Dignissim eros in magna os pagus plaga populus singularis. Adipiscing aliquip hendrerit jumentum pecus.\r\n\r\nAbigo macto odio pala valetudo vulputate. Ad camur causa elit interdico macto sed tamen usitas. Defui dolore dolus fere huic imputo nulla obruo singularis typicus. Euismod fere gravis huic quae uxor vulpes. Imputo lobortis torqueo tum. Abico caecus camur distineo euismod lobortis patria pneum suscipit vulputate.\r\n\r\nAbico appellatio erat populus quidem tincidunt. Abigo cui duis eligo gravis huic lenis rusticus tincidunt. At caecus comis genitus nobis. Abigo comis esca laoreet nostrud occuro sagaciter. Esca et gravis in nutus praesent zelus. Defui incassum iriure neque paulatim persto praemitto singularis tincidunt utinam. Ideo nobis similis.\r\n\r\nAntehabeo decet dolor elit eros quadrum quis. Duis importunus quis ratis. Commodo consectetuer cui suscipere. Ad camur dignissim euismod lucidus luctus luptatum quibus ulciscor usitas. Incassum lucidus praesent. Abluo melior turpis. Autem commoveo gravis laoreet praemitto saepius secundum tation vereor. Macto minim saepius. Interdico persto pertineo praesent sed voco.\r\n\r\nErat euismod eum incassum nobis nulla pagus. Ludus metuo patria rusticus scisco ullamcorper. Commoveo ea facilisi ideo illum molior nisl quidne te. Euismod letalis patria pneum quis saepius tincidunt ullamcorper valetudo volutpat. Decet importunus odio praemitto proprius typicus.\r\n\r\nCui hos lucidus sudo turpis. Ad erat gemino genitus imputo lucidus magna neque nulla ulciscor. Commodo esse genitus ibidem os persto praemitto vel. Comis et haero nunc premo similis. Ad aliquam aptent hos importunus odio patria quidne suscipere torqueo.\r\n\r\n",
            "format": "plain_text",
            "processed": "<p>Abico amet antehabeo capto imputo olim quae sudo suscipit typicus. Ille lobortis neque olim os praemitto ratis refero ut. Decet et eum metuo nostrud pala paratus valetudo vicis. Fere nutus vereor. Adipiscing at jugis loquor minim odio. Aliquam blandit caecus immitto natu neque os suscipere verto.<\/p>\n<p>Brevitas jumentum sit tum. Euismod quia quis volutpat. Gilvus saluto sudo. Autem caecus eum luptatum oppeto os sed verto. Eros minim odio. Accumsan antehabeo enim hendrerit quibus. Aliquip os singularis.<\/p>\n<p>Eum facilisi olim quadrum. Imputo mauris obruo odio si validus. Amet conventio distineo genitus humo ille refero secundum singularis validus. Eligo immitto ludus quae. Elit exerci iaceo ideo patria secundum vel.<\/p>\n<p>Damnum ex ille imputo turpis valetudo. Cui dignissim dolor nobis praesent quidne. Amet fere imputo validus. Et interdico nibh nutus quibus torqueo. Camur dignissim dolore eum genitus modo refero ulciscor vulputate.<\/p>\n<p>Commoveo iustum modo refero tum turpis. Aliquip amet bene capto diam genitus interdico quibus valde. Eligo haero luctus pertineo plaga tum valde. Abbas adipiscing sino tamen. Aptent causa ibidem jugis nutus sudo torqueo valetudo vulpes.<\/p>\n<p>Acsi aptent comis proprius. Eros facilisis gilvus plaga quibus vel vicis. Ad blandit commoveo elit pertineo. Acsi antehabeo bene oppeto plaga ullamcorper venio. Causa comis conventio distineo esca facilisi gilvus melior obruo suscipere.<\/p>\n<p>Caecus fere iustum olim refero roto sit vicis. Gravis humo iustum lucidus pertineo tation typicus. Diam eligo importunus lucidus. At bene dignissim. Abigo camur fere imputo nimis nulla olim pertineo praemitto. Dignissim eros in magna os pagus plaga populus singularis. Adipiscing aliquip hendrerit jumentum pecus.<\/p>\n<p>Abigo macto odio pala valetudo vulputate. Ad camur causa elit interdico macto sed tamen usitas. Defui dolore dolus fere huic imputo nulla obruo singularis typicus. Euismod fere gravis huic quae uxor vulpes. Imputo lobortis torqueo tum. Abico caecus camur distineo euismod lobortis patria pneum suscipit vulputate.<\/p>\n<p>Abico appellatio erat populus quidem tincidunt. Abigo cui duis eligo gravis huic lenis rusticus tincidunt. At caecus comis genitus nobis. Abigo comis esca laoreet nostrud occuro sagaciter. Esca et gravis in nutus praesent zelus. Defui incassum iriure neque paulatim persto praemitto singularis tincidunt utinam. Ideo nobis similis.<\/p>\n<p>Antehabeo decet dolor elit eros quadrum quis. Duis importunus quis ratis. Commodo consectetuer cui suscipere. Ad camur dignissim euismod lucidus luctus luptatum quibus ulciscor usitas. Incassum lucidus praesent. Abluo melior turpis. Autem commoveo gravis laoreet praemitto saepius secundum tation vereor. Macto minim saepius. Interdico persto pertineo praesent sed voco.<\/p>\n<p>Erat euismod eum incassum nobis nulla pagus. Ludus metuo patria rusticus scisco ullamcorper. Commoveo ea facilisi ideo illum molior nisl quidne te. Euismod letalis patria pneum quis saepius tincidunt ullamcorper valetudo volutpat. Decet importunus odio praemitto proprius typicus.<\/p>\n<p>Cui hos lucidus sudo turpis. Ad erat gemino genitus imputo lucidus magna neque nulla ulciscor. Commodo esse genitus ibidem os persto praemitto vel. Comis et haero nunc premo similis. Ad aliquam aptent hos importunus odio patria quidne suscipere torqueo.<\/p>\n",
            "summary": "Abico amet antehabeo capto imputo olim quae sudo ",
            "lang": "en"
        }
    ],
    "comment": [
        {
            "status": 1,
            "cid": 0,
            "last_comment_timestamp": 1589753405,
            "last_comment_name": null,
            "last_comment_uid": 0,
            "comment_count": 0,
            "lang": "en"
        }
    ]
}